{"top":"global.DesignTop",
"namespaces":{
  "global":{
    "modules":{
      "DesignTop":{
        "type":["Record",[
          ["in",["Record",[["arg_1",["Array",1,["Array",1,["Array",16,"BitIn"]]]]]]],
          ["out",["Array",1,["Array",1,["Array",16,"Bit"]]]]
        ]],
        "instances":{
          "add_305_309_310":{
            "genref":"coreir.add",
            "genargs":{"width":["Int",16]}
          },
          "add_311_315_316":{
            "genref":"coreir.add",
            "genargs":{"width":["Int",16]}
          },
          "const0__304":{
            "genref":"coreir.const",
            "genargs":{"width":["Int",16]},
            "modargs":{"value":[["BitVector",16],"16'h000000000000"]}
          },
          "const5__308":{
            "genref":"coreir.const",
            "genargs":{"width":["Int",16]},
            "modargs":{"value":[["BitVector",16],"16'h000000000005"]}
          },
          "const5__314":{
            "genref":"coreir.const",
            "genargs":{"width":["Int",16]},
            "modargs":{"value":[["BitVector",16],"16'h000000000005"]}
          },
          "lb_p4_clamped_stencil_update_stream":{
            "genref":"commonlib.linebuffer2d",
            "genargs":{"bitwidth":["Int",16], "image_width":["Int",9], "stencil_height":["Int",1], "stencil_width":["Int",2]}
          },
          "lb_p4_clamped_stencil_update_stream_wen":{
            "modref":"corebit.const",
            "modargs":{"value":["Bool",true]}
          },
          "mul_307_308_309":{
            "genref":"coreir.mul",
            "genargs":{"width":["Int",16]}
          },
          "mul_313_314_315":{
            "genref":"coreir.mul",
            "genargs":{"width":["Int",16]}
          },
          "pt_conv1_2_stencil":{
            "genref":"mantle.wire",
            "genargs":{"type":["CoreIRType",["Array",1,["Array",1,["Array",16,"Bit"]]]]}
          },
          "pt_conv1_2_stencil$1":{
            "genref":"mantle.wire",
            "genargs":{"type":["CoreIRType",["Array",1,["Array",1,["Array",16,"Bit"]]]]}
          },
          "pt_conv1_2_stencil$2":{
            "genref":"mantle.wire",
            "genargs":{"type":["CoreIRType",["Array",1,["Array",1,["Array",16,"Bit"]]]]}
          },
          "pt_hw_output_2_stencil":{
            "genref":"mantle.wire",
            "genargs":{"type":["CoreIRType",["Array",1,["Array",1,["Array",16,"Bit"]]]]}
          }
        },
        "connections":[
          ["add_305_309_310.in0","pt_conv1_2_stencil.out.0.0"],
          ["add_305_309_310.in1","mul_307_308_309.out"],
          ["add_305_309_310.out","pt_conv1_2_stencil$1.in.0.0"],
          ["add_311_315_316.in0","pt_conv1_2_stencil$1.out.0.0"],
          ["add_311_315_316.in1","mul_313_314_315.out"],
          ["add_311_315_316.out","pt_conv1_2_stencil$2.in.0.0"],
          ["const0__304.out","pt_conv1_2_stencil.in.0.0"],
          ["const5__308.out","mul_307_308_309.in1"],
          ["const5__314.out","mul_313_314_315.in1"],
          ["lb_p4_clamped_stencil_update_stream.in","self.in.arg_1.0.0"],
          ["lb_p4_clamped_stencil_update_stream.wen","lb_p4_clamped_stencil_update_stream_wen.out"],
          ["mul_307_308_309.in0","lb_p4_clamped_stencil_update_stream.out.0.0"],
          ["mul_313_314_315.in0","lb_p4_clamped_stencil_update_stream.out.0.1"],
          ["pt_hw_output_2_stencil.out","self.out"],
          ["pt_conv1_2_stencil$2.out.0.0","pt_hw_output_2_stencil.in.0.0"]
        ]
      }
    }
  }
}
}